baredSC/__init__.py
baredSC/_version.py
baredSC/baredSC_1d.py
baredSC/baredSC_2d.py
baredSC/combineMultipleModels_1d.py
baredSC/combineMultipleModels_2d.py
baredSC/common.py
baredSC/oned.py
baredSC/twod.py
baredSC-1.1.3.data/scripts/baredSC_1d
baredSC-1.1.3.data/scripts/baredSC_2d
baredSC-1.1.3.data/scripts/combineMultipleModels_1d
baredSC-1.1.3.data/scripts/combineMultipleModels_2d
baredSC-1.1.3.dist-info/LICENSE
baredSC-1.1.3.dist-info/METADATA
baredSC-1.1.3.dist-info/WHEEL
baredSC-1.1.3.dist-info/top_level.txt
baredSC-1.1.3.dist-info/RECORD
