Metadata-Version: 2.1
Name: baredSC
Version: 1.1.3
Summary: baredSC: Bayesian Approach to Retreive Expression Distribution of Single Cell
Home-page: https://github.com/lldelisle/baredSC
Author: Lucille Lopez-Delisle, Jean-Baptiste Delisle
Author-email: lucille.delisle@epfl.ch
License: GPLv3
Project-URL: Bug Tracker, https://github.com/lldelisle/baredSC/issues
Project-URL: Documentation, https://baredsc.readthedocs.io/en/v1.1.3
Classifier: Intended Audience :: Science/Research
Classifier: Topic :: Scientific/Engineering :: Bio-Informatics
Requires-Python: >=3.7, <4
License-File: LICENSE
Requires-Dist: numpy >=1.16
Requires-Dist: matplotlib >=3.1.1
Requires-Dist: pandas >=0.25.0
Requires-Dist: scipy >=1.3.0
Requires-Dist: corner >=2.0.0
Requires-Dist: samsam >=0.1.2
Requires-Dist: anndata >=0.7
